dwj_tools/Lib_OptionCalculator.py
dwj_tools/__init__.py
dwj_tools/data_process.py
dwj_tools/p4f.py
dwj_tools-0.0.1.dist-info/METADATA
dwj_tools-0.0.1.dist-info/WHEEL
dwj_tools-0.0.1.dist-info/entry_points.txt
dwj_tools-0.0.1.dist-info/top_level.txt
dwj_tools-0.0.1.dist-info/RECORD
