Metadata-Version: 2.1
Name: dwj-tools
Version: 0.0.1
Summary: 私人
Home-page: https://github.com/Coxhuang/get_time
Author: 丁文杰
Author-email: 359582058@qq.com
License: UNKNOWN
Platform: UNKNOWN
